odoo/addons/maintenance_request_repair/README.rst
odoo/addons/maintenance_request_repair/__init__.py
odoo/addons/maintenance_request_repair/__manifest__.py
odoo/addons/maintenance_request_repair/i18n/it.po
odoo/addons/maintenance_request_repair/i18n/maintenance_request_repair.pot
odoo/addons/maintenance_request_repair/i18n/pt_BR.po
odoo/addons/maintenance_request_repair/models/__init__.py
odoo/addons/maintenance_request_repair/models/maintenance_request.py
odoo/addons/maintenance_request_repair/models/repair_order.py
odoo/addons/maintenance_request_repair/readme/CONTRIBUTORS.rst
odoo/addons/maintenance_request_repair/readme/DESCRIPTION.rst
odoo/addons/maintenance_request_repair/readme/USAGE.rst
odoo/addons/maintenance_request_repair/static/description/icon.png
odoo/addons/maintenance_request_repair/static/description/index.html
odoo/addons/maintenance_request_repair/views/maintenance_request.xml
odoo/addons/maintenance_request_repair/views/repair_order.xml
odoo12_addon_maintenance_request_repair-12.0.1.0.0.99.dev13.dist-info/METADATA
odoo12_addon_maintenance_request_repair-12.0.1.0.0.99.dev13.dist-info/WHEEL
odoo12_addon_maintenance_request_repair-12.0.1.0.0.99.dev13.dist-info/top_level.txt
odoo12_addon_maintenance_request_repair-12.0.1.0.0.99.dev13.dist-info/RECORD
